src/__init__.py
src/root2hdf5.py
tests/__init__.py
tests/test_root2hdf5.py
root2hdf5-0.1.6.dist-info/LICENSE
root2hdf5-0.1.6.dist-info/METADATA
root2hdf5-0.1.6.dist-info/WHEEL
root2hdf5-0.1.6.dist-info/entry_points.txt
root2hdf5-0.1.6.dist-info/top_level.txt
root2hdf5-0.1.6.dist-info/RECORD
