Metadata-Version: 2.1
Name: root2hdf5
Version: 0.1.6
Summary: Lightweight ROOT to HDF5 file converter
Home-page: https://github.com/dev-geof/root2hdf5
Author: Geoffrey Gilles
Classifier: Programming Language :: Python :: 3
Classifier: License :: OSI Approved :: MIT License
Classifier: Operating System :: OS Independent
Classifier: Intended Audience :: Science/Research
Classifier: Topic :: Scientific/Engineering
Requires-Python: >=3.9.13
License-File: LICENSE
Requires-Dist: uproot ==5.0.4
Requires-Dist: h5py ==3.8.0
Requires-Dist: numpy ==1.24.2
Requires-Dist: tqdm ==4.66.3
